skycalc_ipy/__init__.py
skycalc_ipy/core.py
skycalc_ipy/params.yaml
skycalc_ipy/tests/test_core.py
skycalc_ipy/tests/test_ui.py
skycalc_ipy/ui.py
skycalc_ipy-0.7.0.dist-info/LICENSE
skycalc_ipy-0.7.0.dist-info/METADATA
skycalc_ipy-0.7.0.dist-info/WHEEL
skycalc_ipy-0.7.0.dist-info/RECORD
