Metadata-Version: 2.3
Name: skycalc-ipy
Version: 0.7.0
Summary: Get atmospheric spectral information from the ESO skycalc server.
License: GPL-3.0-or-later
Keywords: astronomy
Author: Kieran Leschinski
Author-email: kieran.leschinski@unive.ac.at
Maintainer: Kieran Leschinski
Maintainer-email: kieran.leschinski@unive.ac.at
Requires-Python: >=3.10,<3.15
Classifier: Intended Audience :: Science/Research
Classifier: License :: OSI Approved :: GNU General Public License v3 or later (GPLv3+)
Classifier: Operating System :: OS Independent
Classifier: Programming Language :: Python :: 3
Classifier: Programming Language :: Python :: 3.10
Classifier: Programming Language :: Python :: 3.11
Classifier: Programming Language :: Python :: 3.12
Classifier: Programming Language :: Python :: 3.13
Classifier: Topic :: Scientific/Engineering :: Astronomy
Provides-Extra: syn
Requires-Dist: astar-utils (>=0.5.0,<1.0)
Requires-Dist: astropy (>=6.1.7,<8.0.0)
Requires-Dist: httpx (>=0.28.1,<1.0)
Requires-Dist: numpy (>=1.26.4,<2.4.0)
Requires-Dist: pyyaml (>=6.0.3,<7.0.0)
Requires-Dist: scipy (>=1.15.3,<1.16.0) ; (python_version == "3.10") and (extra == "syn")
Requires-Dist: scipy (>=1.17.0,<1.18.0) ; (python_version >= "3.11") and (extra == "syn")
Requires-Dist: synphot (>=1.6.1,<2.0.0) ; extra == "syn"
Project-URL: Bug Tracker, https://github.com/AstarVienna/skycalc_ipy/issues
Project-URL: Changelog, https://github.com/AstarVienna/skycalc_ipy/releases
Project-URL: Documentation, https://skycalc-ipy.readthedocs.io/en/latest/
Project-URL: Repository, https://github.com/AstarVienna/skycalc_ipy
